LICENSE
MANIFEST.in
README.md
goodreadsapi.py
setup.py
goodreadsapi.egg-info/PKG-INFO
goodreadsapi.egg-info/SOURCES.txt
goodreadsapi.egg-info/dependency_links.txt
goodreadsapi.egg-info/requires.txt
goodreadsapi.egg-info/top_level.txt